django_dag_postgresql/models.py
django_dag_postgresql-0.0.1.dist-info/LICENSE
django_dag_postgresql-0.0.1.dist-info/METADATA
django_dag_postgresql-0.0.1.dist-info/WHEEL
django_dag_postgresql-0.0.1.dist-info/top_level.txt
django_dag_postgresql-0.0.1.dist-info/RECORD
