Metadata-Version: 2.1
Name: django-dag-postgresql
Version: 0.0.1
Summary: Directed Acyclic Graph implementation for Django / Postgresql
Home-page: https://github.com/worsht/django-dag-postgresql
Author: Rajiv Subrahmanyam
Author-email: rajiv.public@gmail.com
License: Apache Software License
Platform: UNKNOWN
Classifier: Development Status :: 3 - Alpha
Classifier: Intended Audience :: Developers
Classifier: License :: OSI Approved :: Apache Software License
Classifier: Programming Language :: Python
Classifier: Operating System :: OS Independent
Classifier: Topic :: Software Development :: Libraries
Classifier: Topic :: Utilities
Classifier: Environment :: Web Environment
Classifier: Framework :: Django
